{
    "晴":"sunny",
    "多云":"cloudy",
    "雨":"rainy",
    "小雨":"rainy",
    "中雨":"rainy",
    "大雨":"rainy",
    "暴雨":"rainy",
    "大暴雨":"rainy",
    "特大暴雨":"rainy",
    "雾":"cloudy",
    "霾":"cloudy",
    "沙尘暴":"cloudy",
    "大风":"cloudy",
    "寒潮":"cloudy",
    "霜冻":"cloudy",
    "冰雹":"rainy",
    "雷阵雨":"rainy",
    "雷阵雨伴有冰雹":"rainy",
    "雨夹雪":"rainy",
    "小雪":"rainy",
    "中雪":"rainy",
    "大雪":"rainy",
    "暴雪":"rainy",
    "浮尘":"cloudy",
    "扬沙":"cloudy",
    "强沙尘暴":"cloudy",
    "龙卷风":"cloudy",
    "飓风":"cloudy",
    "台风":"cloudy",
    "阴":"cloudy",
    "其他":"other_weather"
}